LICENSE.md
README.md
pyproject.toml
setup.py
ds_format/__init__.py
ds_format/help.py
ds_format/io.py
ds_format/misc.py
ds_format/op.py
ds_format/validate.py
ds_format.egg-info/PKG-INFO
ds_format.egg-info/SOURCES.txt
ds_format.egg-info/dependency_links.txt
ds_format.egg-info/entry_points.txt
ds_format.egg-info/requires.txt
ds_format.egg-info/top_level.txt
ds_format/bin/__init__.py
ds_format/bin/ds.py
ds_format/cmd/__init__.py
ds_format/cmd/attrs.py
ds_format/cmd/cat.py
ds_format/cmd/dim.py
ds_format/cmd/dims.py
ds_format/cmd/ls.py
ds_format/cmd/main.py
ds_format/cmd/merge.py
ds_format/cmd/meta.py
ds_format/cmd/rename.py
ds_format/cmd/rename_dim.py
ds_format/cmd/rm.py
ds_format/cmd/select.py
ds_format/cmd/set_.py
ds_format/cmd/size.py
ds_format/cmd/stats.py
ds_format/cmd/type_.py
ds_format/drivers/__init__.py
ds_format/drivers/csv.py
ds_format/drivers/ds.py
ds_format/drivers/hdf.py
ds_format/drivers/json.py
ds_format/drivers/netcdf.py
man/ds-attrs.1
man/ds-cat.1
man/ds-dim.1
man/ds-dims.1
man/ds-get.1
man/ds-ls.1
man/ds-merge.1
man/ds-meta.1
man/ds-rename.1
man/ds-rename_attr.1
man/ds-rename_dim.1
man/ds-rm.1
man/ds-rm_attr.1
man/ds-select.1
man/ds-set.1
man/ds-set_attrs.1
man/ds-set_dims.1
man/ds-size.1
man/ds-stats.1
man/ds-type.1
man/ds-write.1
man/ds.1