Metadata-Version: 2.1
Name: ds-format
Version: 4.3.0
Summary: ds-format is an open source program, a Python package and a storage format which provides an interface for reading and writing NetCDF files, as well as its own data file format.
Home-page: https://ds-format.peterkuma.net
Author: Peter Kuma
Author-email: peter@peterkuma.net
License: MIT
Keywords: dataset,netcdf,hdf,json,numpy
Platform: any
Classifier: Development Status :: 5 - Production/Stable
Classifier: Intended Audience :: Science/Research
Classifier: License :: OSI Approved :: MIT License
Classifier: Operating System :: OS Independent
Classifier: Programming Language :: Python :: 3
Requires-Python: >=3.0
License-File: LICENSE.md
